{
  "appPageId" : "e6b54c1f-02fb-4681-8173-389fc2877ebc",
  "componentName" : "siteforce:sldsOneColLayout",
  "dataProviders" : [ ],
  "id" : "c7c9f883-3b6a-4ac6-ad6f-9ecda66d8987",
  "label" : "File List",
  "regions" : [ {
    "id" : "3a027110-77be-4fae-90f1-94786a454f65",
    "regionName" : "header",
    "type" : "region"
  }, {
    "components" : [ {
      "componentAttributes" : {
        "pageSize" : 25
      },
      "componentName" : "forceCommunity:filesList",
      "id" : "abc20ba0-565b-4071-8f10-713172ecd4c8",
      "renderPriority" : "NEUTRAL",
      "renditionMap" : { },
      "type" : "component"
    } ],
    "id" : "ca4dbddf-9f0f-467f-9953-710c66900069",
    "regionName" : "content",
    "type" : "region"
  }, {
    "id" : "ab94a775-62a0-487b-8407-4dd262290d6c",
    "regionName" : "footer",
    "type" : "region"
  } ],
  "themeLayoutType" : "Inner",
  "type" : "view",
  "viewType" : "list-069"
}