{
  "appPageId" : "e6b54c1f-02fb-4681-8173-389fc2877ebc",
  "componentName" : "siteforce:sldsOneColLayout",
  "dataProviders" : [ ],
  "id" : "ec453ff4-471d-4366-930f-0b969f21e715",
  "label" : "Group List",
  "regions" : [ {
    "id" : "d6030a7c-efa1-4cdf-be17-4c0809522c65",
    "regionName" : "header",
    "type" : "region"
  }, {
    "components" : [ {
      "componentAttributes" : {
        "richTextValue" : "             <h1 style=\"text-align: center;\">                 <b style=\"font-size: 20px; color: #1e2443;\">Group List</b>             </h1>             "
      },
      "componentName" : "forceCommunity:richTextInline",
      "id" : "f22a0e4c-1626-4f1f-a7db-e8673724bfaf",
      "renderPriority" : "NEUTRAL",
      "renditionMap" : { },
      "type" : "component"
    }, {
      "componentAttributes" : { },
      "componentName" : "forceCommunity:groupObjectHome",
      "id" : "5f7bc65e-c482-4c90-9eb1-8e3af2c95c49",
      "renderPriority" : "NEUTRAL",
      "renditionMap" : { },
      "type" : "component"
    } ],
    "id" : "c18b4b00-1f3c-4bb8-99ad-e9b5d06b198b",
    "regionName" : "content",
    "type" : "region"
  }, {
    "id" : "4d4591cf-b522-4677-94db-3f0761a7e90c",
    "regionName" : "footer",
    "type" : "region"
  } ],
  "themeLayoutType" : "Inner",
  "type" : "view",
  "viewType" : "list-0F9"
}