{
  "appPageId" : "f65e262b-e52a-4cbd-8ec7-1040be924555",
  "componentName" : "siteforce:sldsOneColLayout",
  "dataProviders" : [ ],
  "id" : "8b961858-74a9-4915-a30b-ab959ae7642f",
  "label" : "Login Error",
  "regions" : [ {
    "id" : "d4e143e3-af09-4359-8593-dc99039527a8",
    "regionName" : "header",
    "type" : "region"
  }, {
    "components" : [ {
      "componentAttributes" : {
        "richTextValue" : "<div style=\"text-align: center;\">Invalid Page</div>"
      },
      "componentName" : "forceCommunity:richTextInline",
      "id" : "e7f6d733-b618-4e72-9e50-a3b8b8ab1acc",
      "renderPriority" : "NEUTRAL",
      "renditionMap" : { },
      "type" : "component"
    } ],
    "id" : "c037064a-16cc-4819-ae5c-812358653d3d",
    "regionName" : "content",
    "type" : "region"
  }, {
    "id" : "1caeee88-5f00-43c7-9bb4-6ae2304069e4",
    "regionName" : "footer",
    "type" : "region"
  }, {
    "components" : [ {
      "componentAttributes" : {
        "customHeadTags" : "",
        "description" : "",
        "title" : "Login Error"
      },
      "componentName" : "forceCommunity:seoAssistant",
      "id" : "aef66aab-7a02-447d-b8ac-3f585da42bf6",
      "renditionMap" : { },
      "type" : "component"
    } ],
    "id" : "0b094de1-f377-4af7-bdae-67aae8f27389",
    "regionName" : "sfdcHiddenRegion",
    "type" : "region"
  } ],
  "themeLayoutType" : "Login",
  "type" : "view",
  "viewType" : "login-error"
}