{
  "appPageId" : "e6b54c1f-02fb-4681-8173-389fc2877ebc",
  "componentName" : "siteforce:sldsOneColLayout",
  "dataProviders" : [ ],
  "id" : "6a30f106-e6ae-4c10-8e91-dad3abcb3ef8",
  "label" : "Stream Related List",
  "regions" : [ {
    "id" : "0db89d12-f55c-46be-b604-d11bdd74fa72",
    "regionName" : "header",
    "type" : "region"
  }, {
    "id" : "c5a427dc-ecde-46a9-bb1e-45b290b0b95d",
    "regionName" : "content",
    "type" : "region"
  }, {
    "id" : "a7776132-f501-4291-9adf-241f77096305",
    "regionName" : "footer",
    "type" : "region"
  } ],
  "themeLayoutType" : "Inner",
  "type" : "view",
  "viewType" : "relatedlist-0Fq"
}